{     
                "abiu": ["Pouteria caimito","Vú sữa hoàng kim"],
                "acerola": ["Malpighia emarginata","Sơ ri"],
                "ackee": ["Blighia sapida",""],
                "ambarella": ["Spondias dulcis","Cóc"],
                "apple": ["Malus domestica","Táo"],
                "apricot": ["Prunus armeniaca","Mơ Armenia"],
                "avocado": ["Persea americana","Bơ"],
                "banana": ["Musaceae","Họ Chuối"],
                "barbadine": ["Passiflora quadrangularis","Lạc tiên bốn cạnh"],
                "barberry": ["Berberis","Hoàng liên gai"],
                "bayberry": ["Myrica","Chi Thanh mai"],
                "bearberry": ["Arctostaphylos","Dâu gấu"],
                "bell pepper": ["Capsicum annuum","Ớt chuông"],
                "bilimbi": ["Averrhoa bilimbi ","Khế tàu"],
                "bitter gourd": ["Momordica charantia ","Khổ qua"],
                "black berry": ["Rubus subg. Rubus","Mâm xôi đen "],
                "black currant": ["Ribes nigrum","Lý chua đen"],
                "black mullberry": ["Morus nigra","Dâu tằm đen"],
                "black sapote": ["Diospyros nigra","Thị đen"],
                "blueberry": ["Vaccinium sect. Cyanococcus","Việt quất "],
                "bottle gourd": ["Lagenaria siceraria","Bầu"],
                "brazil nut": ["Bertholletia excelsa","Điều Brasil "],
                "bread fruit": ["Artocarpus altilis","Sa kê"],
                "buddha's hand": ["Citrus medica var. sarcodactylis","Phật thủ"],
                "camu camu": ["Myrciaria dubia","Camu camu"],
                "canistel": ["Pouteria campechiana","Canistel"],
                "cantaloupe": ["Cucumis melo var. cantalupensis","Dưa vàng"],
                "cape gooseberry": ["Physalis peruviana","Thù lù lông"],
                "carambola": ["Averrhoa carambola","Khế"],
                "cashew": ["Anacardium occidentale","Điều, đào lộn hột"],
                "cedar bay cherry": ["Eugenia reinwardtiana","Cedar Bay Cherry"],
                "cempedak": ["Artocarpus integer","Mít tố nữ"],
                "chenet": ["Melicoccus bijugatus ","Chanh Tây Ban Nha"],
                "cherimoya": ["Annona cherimola","Mãng cầu tây(Cherimoya)"],
                "cherry": ["Prunus subg. Cerasus","Anh đào"],
                "cloudberry": ["Rubus chamaemorus","Mâm xôi Finnmark"],
                "cluster fig": ["Ficus racemosa","Sung"],
                "cocoa bean": ["Theobroma cacao","Hạt cacao"],
                "coconut": ["Cocos nucifera","Dừa"],
                "coffee": ["Coffea","Cà phê"],
                "corn kernel": ["Zea mays","Ngô"],
                "cranberry": ["Vaccinium subg. Oxycoccus","Mạn việt quất"],
                "crowberry": ["Empetrum nigrum","Crowberry"],
                "cupuacu": ["Theobroma grandiflorum","Cupuacu"],
                "custard apple": ["Annona squamosa","Na, Mãng cầu"],
                "damson": ["Prunus domestica subsp. insititia","Mận damson"],
                "date": ["Phoenix dactylifera","Chà là"],
                "desert lime": ["Citrus glauca","Chanh sa mạc"],
                "dragonfruit": ["Selenicereus undatus","Thanh long"],
                "durian": ["Durio zibethinus","Sầu riêng"],
                "eggplant": ["Cà tím","Solanum melongena"],
                "elderberry": ["Sambucus","Cơm cháy "],
                "elephant apple": ["Dillenia indica","Sổ bà"],
                "emblic": ["Phyllanthus emblica","Me rừng"],
                "entawak": ["Artocarpus anisophyllus","entawak"],
                "etrog": ["Citrus medica ","Thanh yên"],
                "feijoa": ["Acca sellowiana","Ổi dứa "],
                "fig": ["Ficus carica","Vả tây"],
                "finger lime": ["Citrus australasica","Chanh móng tay"],
                "gac": ["Momordica cochinchinensis","Gấc"],
                "galia melon": ["Cucumis melo var. reticulatus","Dưa galia"],
                "goji": ["Lycium sinense ","Câu kỷ tử"],
                "grape": ["Vitis","Nho"],
                "grapefruit": ["Citrus × paradisi","Bưởi chùm"],
                "greengage": ["Prunus domestica subsp. italica","Mận lục"],
                "grenadilla": ["Passiflora ligularis","grenadilla"],
                "guanabana": ["Annona muricata","Mãng cầu Xiêm"],
                "guarana": ["Paullinia cupana","Guarana"],
                "guava": ["Psidium","Ổi"],
                "hard kiwi": ["",""],
                "hawthorn": ["Crataegus","Sơn tra "],
                "hog plum": ["Spondias mombin","Cóc Thái"],
                "honeyberry": ["","honeyberry"],
                "horned melon": ["Cucumis metuliferus","horned melon"],
                "indian almond": ["Terminalia catappa","Bàng "],
                "ita palm": ["Mauritia flexuosa","ita palm"],
                "jaboticaba": ["Plinia cauliflora","jaboticaba"],
                "jackfruit": ["Artocarpus heterophyllus","Mít"],
                "jalapeno": ["Capsicum annuum 'Jalapeño'","Jalapeño"],
                "jamaica cherry": ["Muntingia calabura","Trứng cá"],
                "jambul": ["Syzygium cumini","Trâm mốc"],
                "japanese raisin": ["Hovenia dulcis","Nho khô phương Đông"],
                "jatoba": ["","jatoba"],
                "jocote": ["Spondias purpurea","jocote"],
                "jujube": ["Ziziphus jujuba Mill","Táo tàu"],
                "juniper berry": ["Juniper","Quả bách xù"],
                "kaffir lime": ["Citrus hystrix","Trúc, Chanh Thái"],
                "kakadu plum": ["Terminalia ferdinandiana","Mận Kakadu"],
                "kiwi": ["Actinidia deliciosa","Kiwi"],
                "kumquat": ["Citrus japonica","Kim quất tròn"],
                "langsat": ["Lansium domesticum","Bòn bon"],
                "lemon": ["Citrus limon","Chanh vàng"],
                "leucaena": ["Leucaena","Keo dậu"],
                "lime": ["Citrus × aurantiifolia","Chanh"],
                "loganberry": ["Rubus × loganobaccus","Mâm xôi"],
                "longan": ["Dimocarpus longan","Nhãn"],
                "loquat": ["Eriobotrya japonica","Nhót tây"],
                "lucuma": ["Pouteria lucuma","Lêkima"],
                "lychee": ["Litchi chinensis","Vải"],
                "mabolo": ["Diospyros blancoi","Mabolo "],
                "macadamia": ["Macadamia","Mắc ca"],
                "malay apple": ["Syzygium malaccense","Roi hoa đỏ, mận đỏ"],
                "mandarine": ["Citrus reticulata","Quýt"],
                "mango": ["Mangifera indica","Xoài"],
                "mangosteen": ["Garcinia mangostana","Măng cụt"],
                "manila tamarind": ["Pithecellobium dulce","Me nước "],
                "marang": ["Artocarpus odoratissimus","marang"],
                "melinjo": ["Gnetum gnemon","Gắm"],
                "melon pear": ["Solanum muricatum","Dưa hấu vàng Pepino"],
                "midyim": ["","midyim "],
                "miracle fruit": ["Synsepalum dulcificum","Thần kỳ"],
                "monkfruit": ["Siraitia grosvenorii","La hán quả"],
                "monstera deliciosa": ["Monstera deliciosa","monstera deliciosa"],
                "morinda": ["Morinda","Nhàu"],
                "mundu": ["Garcinia dulcis","mundu"],
                "muskmelon": ["Cucumis melo","Dưa lưới"],
                "naranjilla": ["Solanum quitoense","naranjilla"],
                "nectarine": ["Prunus persica var. nucipersica","Xuân đào"],
                "neem": ["Azadirachta indica","Sầu đâu"],
                "nutmeg": ["Myristica fragrans Houtt","Nhục đậu khấu"],
                "oil palm": ["Elaeis guineensis","Dầu cọ"],
                "olive": ["Olea europaea","Ô liu"],
                "orange": ["Citrus reticulata × sinensis","Cam"],
                "papaya": ["Carica papaya","Đu đủ "],
                "passion fruit": ["Passiflora edulis","Chanh dây"],
                "pawpaw": ["Asimina","Chuối Paw Paw"],
                "pea": ["",""],
                "peanut": ["Arachis hypogaea","Lạc, đậu phộng"],
                "pear": ["Pyrus","Lê "],
                "persimmon": ["Diospyros kaki","Quả hồng"],
                "pineapple": ["Ananas comosus","Dứa"],
                "pineberry": ["Fragaria x ananassa Pineberry","Dâu tây trắng"],
                "pomegranate": ["Punica granatum","Lựu "],
                "pomelo": ["Citrus maxima","Bưởi"],
                "pulasan": ["Nephelium mutabile ","pulasan"],
                "pumpkin": ["Cucurbita pepo","Bí ngô "],
                "purple apple berry": ["Billardiera longiflora","purple apple berry"],
                "quandong": ["Santalum acuminatum","Quandong"],
                "quince": ["Cydonia oblonga","Mộc qua Kavkaz"],
                "rambutan": ["Nephelium lappaceum","Chôm chôm"],
                "rangpur": ["Citrus × limonia","Chanh kiên"],
                "redcurrant": ["Ribes rubrum","Lý chua đỏ "],
                "ridged gourd": ["Luffa acutangula","Mướp khía"],
                "rose hip": ["Rosa canina L.","Quả tầm xuân"],
                "rose myrtle": ["Rhodomyrtus tomentosa","Sim"],
                "salak": ["Salacca zalacca","Quả salak"],
                "salmonberry": ["Rubus spectabilis ","Mâm xôi hồi"],
                "santol": ["Sandoricum koetjape","Sấu đỏ"],
                "sapodilla": ["Manilkara zapota","Hồng xiêm, saboche"],
                "sea buckthorn": ["Hippophae Rhamnoides","Hắc mai biển"],
                "sea grape": ["Caulerpa lentillifera","Rong nho "],
                "snowberry": ["Symphoricarpos","Bạch việt quất"],
                "strawberry": ["Fragaria × ananassa","Dâu tây "],
                "strawberry guava": ["Psidium cattleianum","Ổi sẻ"],
                "surinam cherry": ["Eugenia uniflora","Trâm sơ ri"],
                "tangelo": ["Citrus × tangelo","Quýt bưởi"],
                "taxus baccata": ["Taxus baccata","Thanh tùng châu Âu"],
                "texas persimmon": ["Diospyros texana","Thị Texax "],
                "tomato": ["Solanum lycopersicum","Cà chua"],
                "ugli fruit": ["Citrus reticulata × paradisi","Chanh Tây Ấn"],
                "vanilla": ["Vanilla orchids","Vani"],
                "velvet tamarind": ["Dialium cochinchinense","Xoay"],
                "vú sữa": ["Chrysophyllum cainito","Vú sữa"],
                "watermelon": ["Citrullus lanatus","Dưa hấu "],
                "wax gourd": ["Benincasa hispida","Bí đao "],
                "white currant": ["Ribes rubrum 'White Grape'","Lý chùm trắng"],
                "white mulberry": ["Morus alba","Dâu tằm trắng"],
                "white sapote": ["Casimiroa edulis","hồng trắng "],
                "yali pear": ["Pyrus pyrifolia 'Yali'","yali pear"],
                "yellow plum": ["Prunus domestica subsp. syriaca","Mận Mirabelle "],
                "yuzu": ["Citrus junos","Yuzu "],
                "zucchini": ["Zucchini","Bí ngòi"]
}